<annotation text="Abstract The photodissociation of Ar3+ is studied following a consistent theoretical approach from the Potential Energy Surfaces to the dynamics. Six P.E.S. are computed according to a D.I.M.-like model Hamiltonian. Transition dipole moments are determined using a similar method. The 4-D dynamics of this system is obtained with the H.W.D. method (Hemiquantal dynamic with the Whole DIM basis). All the 4 nuclear degrees of freedom and all the 6 electronic states are involved in the dynamical calculations, allowing for very general investigations. The main theoretical results are:1the spectrum essentially results from a Σ → Σg transition to the second excited electronic state along with a symmetric stretching motion2excited Ar3+ molecules almost all dissociate in Ar+ + 2 Ar3dissociation in Ar2+ + Ar requires special conditions such as low laser excitation and is predicted to increase with a specific excitation of the bending mode4the dominant symmetric stretching motion induces a bimodal kinetic energy distribution of the fragments. All these points are in close agreement with experimental results.">
  <surfaceForm name="All" offset="396">
    <resource label="China" uri="China" contextualScore="0.99983990795472" percentageOfSecondRank="4.799964764054567E-6" support="124308" priorScore="0.0010339967050317696" finalScore="0.9999944972008935" types="Schema:Place, DBpedia:Place, DBpedia:PopulatedPlace, Schema:Country, DBpedia:Country"/>
  </surfaceForm>
  <surfaceForm name="motion" offset="975">
    <resource label="Motion (physics)" uri="Motion_(physics)" contextualScore="0.9998665477360201" percentageOfSecondRank="2.09462299420804E-6" support="1396" priorScore="1.1611959006856762E-5" finalScore="0.9999979053806437" types=""/>
  </surfaceForm>
  <surfaceForm name="dynamical" offset="485">
    <resource label="Dynamics (mechanics)" uri="Dynamics_(mechanics)" contextualScore="0.989931182344807" percentageOfSecondRank="0.06712366902113436" support="509" priorScore="4.233873305508662E-6" finalScore="0.9364482928871211" types=""/>
  </surfaceForm>
  <surfaceForm name="symmetric" offset="954">
    <resource label="Symmetry" uri="Symmetry" contextualScore="0.9999992431247073" percentageOfSecondRank="1.6985395692350468E-7" support="2270" priorScore="1.888191041945906E-5" finalScore="0.9999998301459672" types=""/>
  </surfaceForm>
  <surfaceForm name="photodissociation" offset="13">
    <resource label="Photodissociation" uri="Photodissociation" contextualScore="1.0" percentageOfSecondRank="0.0" support="208" priorScore="1.7301486199328126E-6" finalScore="1.0" types=""/>
  </surfaceForm>
  <surfaceForm name="bending" offset="928">
    <resource label="Bending" uri="Bending" contextualScore="0.9984976685469867" percentageOfSecondRank="1.8615540634351652E-5" support="237" priorScore="1.9713712640580605E-6" finalScore="0.9999813845734129" types=""/>
  </surfaceForm>
  <surfaceForm name="The main" offset="551">
    <resource label="Saint Laurent Boulevard" uri="Saint_Laurent_Boulevard" contextualScore="0.9621591124186526" percentageOfSecondRank="0.0" support="117" priorScore="9.732085987122072E-7" finalScore="0.9999999813775278" types="Schema:Place, DBpedia:Place, DBpedia:ArchitecturalStructure, DBpedia:Infrastructure, DBpedia:RouteOfTransportation, DBpedia:Road"/>
  </surfaceForm>
  <surfaceForm name="involved" offset="469">
    <resource label="The Culture" uri="The_Culture" contextualScore="0.9996013156323834" percentageOfSecondRank="2.257260126651934E-5" support="302" priorScore="2.5120427077870646E-6" finalScore="0.9999765354705837" types=""/>
  </surfaceForm>
  <surfaceForm name="dissociate" offset="757">
    <resource label="Dissociation (chemistry)" uri="Dissociation_(chemistry)" contextualScore="0.9999999941210262" percentageOfSecondRank="7.320113204339003E-10" support="257" priorScore="2.1377317082823696E-6" finalScore="0.9999999992679705" types=""/>
  </surfaceForm>
  <surfaceForm name="investigations" offset="535">
    <resource label="Research" uri="Research" contextualScore="0.9542507789106862" percentageOfSecondRank="8.811418389138599E-4" support="9112" priorScore="7.579381838859514E-5" finalScore="0.9991186037133033" types=""/>
  </surfaceForm>
  <surfaceForm name="experimental" offset="1091">
    <resource label="Experiment" uri="Experiment" contextualScore="0.9999491317150493" percentageOfSecondRank="6.329871807474552E-7" support="1933" priorScore="1.6078736934279456E-5" finalScore="0.9999993649570085" types=""/>
  </surfaceForm>
  <surfaceForm name="bimodal" offset="992">
    <resource label="Bimodal distribution" uri="Bimodal_distribution" contextualScore="0.9999999997702389" percentageOfSecondRank="3.5993116065212755E-12" support="78" priorScore="6.488057324748047E-7" finalScore="0.999999999996362" types=""/>
  </surfaceForm>
  <surfaceForm name="molecules" offset="736">
    <resource label="Molecule" uri="Molecule" contextualScore="0.9999999192286882" percentageOfSecondRank="7.028205260141911E-12" support="6324" priorScore="5.260317246372648E-5" finalScore="0.9999999999924967" types=""/>
  </surfaceForm>
  <surfaceForm name="method" offset="273">
    <resource label="Scientific method" uri="Scientific_method" contextualScore="0.007004919041234119" percentageOfSecondRank="0.3861016898868902" support="1645" priorScore="1.3683146537449409E-5" finalScore="0.12148314396933375" types=""/>
    <resource label="Iterative method" uri="Iterative_method" contextualScore="0.9860713793031588" percentageOfSecondRank="0.14711811964047738" support="233" priorScore="1.938099175213199E-6" finalScore="0.8257524244206657" types=""/>
  </surfaceForm>
  <surfaceForm name="spectrum" offset="589">
    <resource label="Spectrum (functional analysis)" uri="Spectrum_(functional_analysis)" contextualScore="0.988599135970901" percentageOfSecondRank="0.07499728188874936" support="239" priorScore="1.9880073084804914E-6" finalScore="0.8719799361550259" types=""/>
  </surfaceForm>
  <surfaceForm name="model" offset="197">
    <resource label="Mathematical model" uri="Mathematical_model" contextualScore="0.9933694048041279" percentageOfSecondRank="0.005545933421044851" support="1147" priorScore="9.540771476264116E-6" finalScore="0.9940855859075178" types=""/>
  </surfaceForm>
  <surfaceForm name="Potential" offset="103">
    <resource label="Electric potential" uri="Electric_potential" contextualScore="0.9958584974528993" percentageOfSecondRank="0.04424042106456564" support="790" priorScore="6.571237546860202E-6" finalScore="0.9576338741805226" types=""/>
  </surfaceForm>
  <surfaceForm name="Abstract" offset="0">
    <resource label="Abstraction" uri="Abstraction" contextualScore="0.9999899297799864" percentageOfSecondRank="6.402084830365531E-5" support="626" priorScore="5.207081904220869E-6" finalScore="0.9999345685242907" types=""/>
  </surfaceForm>
  <surfaceForm name="dipole moments" offset="227">
    <resource label="Electric dipole moment" uri="Electric_dipole_moment" contextualScore="0.6856104161945237" percentageOfSecondRank="3.9646043709480117E-4" support="209" priorScore="1.738466642144028E-6" finalScore="0.1810912000247052" types=""/>
    <resource label="Dipole" uri="Dipole" contextualScore="0.3143225801640648" percentageOfSecondRank="0.2211565906078257" support="773" priorScore="6.429831169269539E-6" finalScore="0.8188370038034816" types=""/>
  </surfaceForm>
  <surfaceForm name="electronic" offset="665">
    <resource label="Electron" uri="Electron" contextualScore="0.9999880139961133" percentageOfSecondRank="2.2338291893344415E-7" support="10107" priorScore="8.407025048875451E-5" finalScore="0.9999997766170986" types=""/>
  </surfaceForm>
  <surfaceForm name="distribution" offset="1015">
    <resource label="Probability distribution" uri="Probability_distribution" contextualScore="0.9818231181569266" percentageOfSecondRank="0.003657845321696302" support="2395" priorScore="1.9921663195860992E-5" finalScore="0.9963554857381229" types=""/>
  </surfaceForm>
  <surfaceForm name="Ar" offset="805">
    <resource label="Argon" uri="Argon" contextualScore="0.9999999984996748" percentageOfSecondRank="2.056295194943881E-11" support="814" priorScore="6.770870079929372E-6" finalScore="0.9999999999794227" types=""/>
  </surfaceForm>
  <surfaceForm name="Ar3" offset="34">
    <resource label="Cytarabine" uri="Cytarabine" contextualScore="0.9999999970094677" percentageOfSecondRank="0.0" support="55" priorScore="4.574912216168495E-7" finalScore="0.9999999999421334" types="DBpedia:Drug"/>
  </surfaceForm>
  <surfaceForm name="electronic" offset="447">
    <resource label="Electron" uri="Electron" contextualScore="0.9999880139961133" percentageOfSecondRank="2.2338291893344415E-7" support="10107" priorScore="8.407025048875451E-5" finalScore="0.9999997766170986" types=""/>
  </surfaceForm>
  <surfaceForm name="dominant" offset="945">
    <resource label="Dominance (genetics)" uri="Dominance_(genetics)" contextualScore="0.9693910690000875" percentageOfSecondRank="0.0015114883598983816" support="3011" priorScore="2.5045564877969705E-5" finalScore="0.9984222424460105" types=""/>
  </surfaceForm>
  <surfaceForm name="Surfaces" offset="120">
    <resource label="Surface" uri="Surface" contextualScore="1.0" percentageOfSecondRank="1.2133450280263987E-22" support="3027" priorScore="2.5178653233349152E-5" finalScore="1.0" types=""/>
  </surfaceForm>
  <surfaceForm name="Hamiltonian" offset="203">
    <resource label="Hamiltonian (quantum mechanics)" uri="Hamiltonian_(quantum_mechanics)" contextualScore="0.026404905669374475" percentageOfSecondRank="0.03573586061211046" support="1080" priorScore="8.983463988112681E-6" finalScore="0.9654971138909231" types=""/>
  </surfaceForm>
  <surfaceForm name="excited" offset="657">
    <resource label="Excited state" uri="Excited_state" contextualScore="0.9999999999879492" percentageOfSecondRank="8.231839835822163E-14" support="565" priorScore="4.699682549336727E-6" finalScore="0.9999999999998863" types=""/>
  </surfaceForm>
  <surfaceForm name="Ar3" offset="731">
    <resource label="Cytarabine" uri="Cytarabine" contextualScore="0.9999999970094677" percentageOfSecondRank="0.0" support="55" priorScore="4.574912216168495E-7" finalScore="0.9999999999421334" types="DBpedia:Drug"/>
  </surfaceForm>
  <surfaceForm name="Ar+" offset="771">
    <resource label="Argon" uri="Argon" contextualScore="1.0" percentageOfSecondRank="0.0" support="814" priorScore="6.770870079929372E-6" finalScore="1.0" types=""/>
  </surfaceForm>
  <surfaceForm name="dynamics" offset="136">
    <resource label="Dynamics (mechanics)" uri="Dynamics_(mechanics)" contextualScore="0.9907289777379029" percentageOfSecondRank="0.0010063518593873189" support="509" priorScore="4.233873305508662E-6" finalScore="0.998498500216715" types=""/>
  </surfaceForm>
  <surfaceForm name="basis" offset="388">
    <resource label="Eigenvalues and eigenvectors" uri="Eigenvalues_and_eigenvectors" contextualScore="0.23065331060985847" percentageOfSecondRank="0.021460090051918224" support="3392" priorScore="2.821473134044279E-5" finalScore="0.9789907696011245" types=""/>
  </surfaceForm>
  <surfaceForm name="dynamic" offset="361">
    <resource label="Dynamics (mechanics)" uri="Dynamics_(mechanics)" contextualScore="0.9932584892334589" percentageOfSecondRank="0.002824277798925608" support="509" priorScore="4.233873305508662E-6" finalScore="0.9971835657268933" types=""/>
  </surfaceForm>
  <surfaceForm name="symmetric" offset="695">
    <resource label="Symmetry" uri="Symmetry" contextualScore="0.9999992431247073" percentageOfSecondRank="1.6985395692350468E-7" support="2270" priorScore="1.888191041945906E-5" finalScore="0.9999998301459672" types=""/>
  </surfaceForm>
  <surfaceForm name="transition" offset="632">
    <resource label="Transition state" uri="Transition_state" contextualScore="0.9999999996722408" percentageOfSecondRank="4.790624992684981E-10" support="565" priorScore="4.699682549336727E-6" finalScore="0.9999999995072812" types=""/>
  </surfaceForm>
  <surfaceForm name="dynamics" offset="289">
    <resource label="Dynamics (mechanics)" uri="Dynamics_(mechanics)" contextualScore="0.9907289777379029" percentageOfSecondRank="0.0010063518593873189" support="509" priorScore="4.233873305508662E-6" finalScore="0.998498500216715" types=""/>
  </surfaceForm>
  <surfaceForm name="nuclear" offset="406">
    <resource label="Atomic nucleus" uri="Atomic_nucleus" contextualScore="0.999999999936108" percentageOfSecondRank="1.6099381703450153E-10" support="2216" priorScore="1.843273722005343E-5" finalScore="0.9999999998389058" types=""/>
  </surfaceForm>
  <surfaceForm name="The" offset="281">
    <resource label="The Miami Herald" uri="The_Miami_Herald" contextualScore="0.4817635539899339" percentageOfSecondRank="0.6416398011855009" support="1081" priorScore="8.991782010323897E-6" finalScore="0.12639823397752128" types="Schema:CreativeWork, DBpedia:Work, DBpedia:WrittenWork, DBpedia:PeriodicalLiterature, DBpedia:Newspaper"/>
    <resource label="Joseph Stalin" uri="Joseph_Stalin" contextualScore="0.5149249167824935" percentageOfSecondRank="0.159524161516252" support="6340" priorScore="5.273626081910593E-5" finalScore="0.7923453900407686" types="DBpedia:Agent, Schema:Person, Http://xmlns.com/foaf/0.1/Person, DBpedia:Person, DBpedia:OfficeHolder"/>
  </surfaceForm>
  <surfaceForm name="Energy" offset="113">
    <resource label="Energy" uri="Energy" contextualScore="1.0" percentageOfSecondRank="1.7579950034035742E-18" support="17356" priorScore="1.4436759349785528E-4" finalScore="1.0" types=""/>
  </surfaceForm>
  <surfaceForm name="induces" offset="982">
    <resource label="Electromagnetic induction" uri="Electromagnetic_induction" contextualScore="0.6320992269368675" percentageOfSecondRank="0.029251042870058842" support="674" priorScore="5.6063469703592105E-6" finalScore="0.9556846391763957" types=""/>
  </surfaceForm>
  <surfaceForm name="calculations" offset="495">
    <resource label="Molecular orbital" uri="Molecular_orbital" contextualScore="0.9999999999903366" percentageOfSecondRank="3.502797594650008E-12" support="454" priorScore="3.7763820838918125E-6" finalScore="0.9999999999964757" types=""/>
  </surfaceForm>
  <surfaceForm name="fragments" offset="1035">
    <resource label="Fragmentation (chemistry)" uri="Fragmentation_(chemistry)" contextualScore="1.0" percentageOfSecondRank="4.832734832749334E-14" support="39" priorScore="3.2440286623740236E-7" finalScore="0.9999999999998863" types=""/>
  </surfaceForm>
  <surfaceForm name="All" offset="1046">
    <resource label="China" uri="China" contextualScore="0.99983990795472" percentageOfSecondRank="4.799964764054567E-6" support="124308" priorScore="0.0010339967050317696" finalScore="0.9999944972008935" types="Schema:Place, DBpedia:Place, DBpedia:PopulatedPlace, Schema:Country, DBpedia:Country"/>
  </surfaceForm>
  <surfaceForm name="system" offset="306">
    <resource label="Dynamical system" uri="Dynamical_system" contextualScore="0.1841051071262658" percentageOfSecondRank="0.42877465039691914" support="1095" priorScore="9.108234321280913E-6" finalScore="0.11860832442694468" types=""/>
    <resource label="Physical system" uri="Physical_system" contextualScore="0.8157646962077177" percentageOfSecondRank="0.1428175692666903" support="402" priorScore="3.3438449289086093E-6" finalScore="0.8304883288236163" types=""/>
  </surfaceForm>
  <surfaceForm name="The" offset="9">
    <resource label="The Miami Herald" uri="The_Miami_Herald" contextualScore="0.4817635539899339" percentageOfSecondRank="0.6416398011855009" support="1081" priorScore="8.991782010323897E-6" finalScore="0.12639823397752128" types="Schema:CreativeWork, DBpedia:Work, DBpedia:WrittenWork, DBpedia:PeriodicalLiterature, DBpedia:Newspaper"/>
    <resource label="Joseph Stalin" uri="Joseph_Stalin" contextualScore="0.5149249167824935" percentageOfSecondRank="0.159524161516252" support="6340" priorScore="5.273626081910593E-5" finalScore="0.7923453900407686" types="DBpedia:Agent, Schema:Person, Http://xmlns.com/foaf/0.1/Person, DBpedia:Person, DBpedia:OfficeHolder"/>
  </surfaceForm>
  <surfaceForm name="predicted" offset="872">
    <resource label="Prediction" uri="Prediction" contextualScore="0.9997332442132708" percentageOfSecondRank="1.2345746730645545E-5" support="462" priorScore="3.842926261581536E-6" finalScore="0.9999876209438943" types=""/>
  </surfaceForm>
  <surfaceForm name="Transition" offset="216">
    <resource label="Transition economy" uri="Transition_economy" contextualScore="0.7742778379895623" percentageOfSecondRank="0.005152559662443172" support="109" priorScore="9.066644210224836E-7" finalScore="0.34789529728842655" types=""/>
    <resource label="Spanish transition to democracy" uri="Spanish_transition_to_democracy" contextualScore="0.21805073092120453" percentageOfSecondRank="0.5350905741103983" support="310" priorScore="2.578586885476788E-6" finalScore="0.6501615130612445" types=""/>
  </surfaceForm>
  <surfaceForm name="laser" offset="848">
    <resource label="Laser" uri="Laser" contextualScore="0.9999999672585324" percentageOfSecondRank="3.832974345275751E-12" support="7268" priorScore="6.045538543111386E-5" finalScore="0.999999999996021" types=""/>
  </surfaceForm>
  <surfaceForm name="DIM" offset="384">
    <resource label="Diminutive" uri="Diminutive" contextualScore="0.017466303708265553" percentageOfSecondRank="0.0" support="746" priorScore="6.205244569566722E-6" finalScore="0.39871716181088074" types=""/>
  </surfaceForm>
  <surfaceForm name="4-" offset="285">
    <resource label="Flat-four engine" uri="Flat-four_engine" contextualScore="0.9987280313253065" percentageOfSecondRank="5.68712460536035E-4" support="230" priorScore="1.9131451085795523E-6" finalScore="0.9994316084153181" types=""/>
  </surfaceForm>
  <surfaceForm name="determined" offset="246">
    <resource label="Determinism" uri="Determinism" contextualScore="0.09227051652160581" percentageOfSecondRank="0.0908215101339564" support="1145" priorScore="9.524135431841686E-6" finalScore="0.916687214207587" types=""/>
  </surfaceForm>
  <surfaceForm name="general" offset="527">
    <resource label="General relativity" uri="General_relativity" contextualScore="1.0" percentageOfSecondRank="4.112946530419938E-17" support="3062" priorScore="2.5469784010741693E-5" finalScore="1.0" types=""/>
  </surfaceForm>
  <surfaceForm name="excitation" offset="854">
    <resource label="Excited state" uri="Excited_state" contextualScore="0.9999999693334307" percentageOfSecondRank="1.7639680020096913E-10" support="565" priorScore="4.699682549336727E-6" finalScore="0.999999999823558" types=""/>
  </surfaceForm>
  <surfaceForm name="computed" offset="161">
    <resource label="Computer simulation" uri="Computer_simulation" contextualScore="0.9999999568161693" percentageOfSecondRank="9.762621007830245E-9" support="943" priorScore="7.843894945176164E-6" finalScore="0.9999999895442215" types=""/>
  </surfaceForm>
  <surfaceForm name="excitation" offset="910">
    <resource label="Excited state" uri="Excited_state" contextualScore="0.9999999693334307" percentageOfSecondRank="1.7639680020096913E-10" support="565" priorScore="4.699682549336727E-6" finalScore="0.999999999823558" types=""/>
  </surfaceForm>
  <surfaceForm name="method" offset="341">
    <resource label="Scientific method" uri="Scientific_method" contextualScore="0.007004919041234119" percentageOfSecondRank="0.3861016898868902" support="1645" priorScore="1.3683146537449409E-5" finalScore="0.12148314396933375" types=""/>
    <resource label="Iterative method" uri="Iterative_method" contextualScore="0.9860713793031588" percentageOfSecondRank="0.14711811964047738" support="233" priorScore="1.938099175213199E-6" finalScore="0.8257524244206657" types=""/>
  </surfaceForm>
  <surfaceForm name="points" offset="1056">
    <resource label="Point (geometry)" uri="Point_(geometry)" contextualScore="0.9999999991816821" percentageOfSecondRank="2.096214670146562E-11" support="2055" priorScore="1.709353564404774E-5" finalScore="0.9999999999624833" types=""/>
  </surfaceForm>
  <surfaceForm name="special" offset="817">
    <resource label="Special relativity" uri="Special_relativity" contextualScore="1.0" percentageOfSecondRank="1.0028219744453625E-18" support="1888" priorScore="1.5704425934774763E-5" finalScore="1.0" types=""/>
  </surfaceForm>
  <surfaceForm name="kinetic energy" offset="1000">
    <resource label="Kinetic energy" uri="Kinetic_energy" contextualScore="1.0" percentageOfSecondRank="1.602351447232875E-22" support="2129" priorScore="1.7709069287677683E-5" finalScore="1.0" types=""/>
  </surfaceForm>
  <surfaceForm name="Six" offset="146">
    <resource label="Number Six (Battlestar Galactica)" uri="Number_Six_(Battlestar_Galactica)" contextualScore="0.989768215683565" percentageOfSecondRank="2.73830567878252E-5" support="362" priorScore="3.0111240404599912E-6" finalScore="0.9999698348959795" types="DBpedia:Agent, Schema:Person, Http://xmlns.com/foaf/0.1/Person, DBpedia:Person, DBpedia:FictionalCharacter"/>
  </surfaceForm>
  <surfaceForm name="specific" offset="901">
    <resource label="Sensitivity and specificity" uri="Sensitivity_and_specificity" contextualScore="0.9995607882906523" percentageOfSecondRank="5.741199029826628E-4" support="762" priorScore="6.338332924946169E-6" finalScore="0.9994261101113922" types=""/>
  </surfaceForm>
  <surfaceForm name="essentially" offset="598">
    <resource label="Almost everywhere" uri="Almost_everywhere" contextualScore="0.9999957728187597" percentageOfSecondRank="9.332177140974466E-6" support="183" priorScore="1.5221980646524265E-6" finalScore="0.9999906679099716" types=""/>
  </surfaceForm>
</annotation>