<annotation text="Abstract Labeling of cells with nanoparticles for living detection is of interest to various biomedical applications. In this study, novel fluorescent/magnetic nanoparticles were prepared and used in high-efficient cellular imaging. The nanoparticles coated with the modified chitosan possessed a magnetic oxide core and a covalently attached fluorescent dye. We evaluated the feasibility and efficiency in labeling cancer cells (SMMC-7721) with the nanoparticles. The nanoparticles exhibited a high affinity to cells, which was demonstrated by flow cytometry and magnetic resonance imaging. The results showed that cell-labeling efficiency of the nanoparticles was dependent on the incubation time and nanoparticles’ concentration. The minimum detected number of labeled cells was around 104by using a clinical 1.5-T MRI imager. Fluorescence and transmission electron microscopy instruments were used to monitor the localization patterns of the magnetic nanoparticles in cells. These new magneto-fluorescent nanoagents have demonstrated the potential for future medical use.">
  <surfaceForm name="magnetic nanoparticles" offset="946">
    <resource label="Magnetic nanoparticles" uri="Magnetic_nanoparticles" contextualScore="1.0" percentageOfSecondRank="0.0" support="33" priorScore="2.744947329701097E-7" finalScore="1.0" types=""/>
  </surfaceForm>
  <surfaceForm name="incubation time" offset="683">
    <resource label="Incubation period" uri="Incubation_period" contextualScore="1.0" percentageOfSecondRank="0.0" support="202" priorScore="1.68024048666552E-6" finalScore="1.0" types=""/>
  </surfaceForm>
  <surfaceForm name="oxide" offset="306">
    <resource label="Oxide" uri="Oxide" contextualScore="0.02224283433333421" percentageOfSecondRank="0.10956089556025649" support="1514" priorScore="1.2593485627780185E-5" finalScore="0.45547095797310033" types=""/>
    <resource label="Oxygen" uri="Oxygen" contextualScore="0.8671944076019666" percentageOfSecondRank="0.9208376904366875" support="13298" priorScore="1.10613059364743E-4" finalScore="0.49462675420801144" types=""/>
  </surfaceForm>
  <surfaceForm name="monitor" offset="905">
    <resource label="Display device" uri="Display_device" contextualScore="0.6228622246148888" percentageOfSecondRank="1.0790047978172426E-4" support="618" priorScore="5.1405377265311456E-6" finalScore="0.11970224824674636" types=""/>
    <resource label="Computer monitor" uri="Computer_monitor" contextualScore="0.37515087640429196" percentageOfSecondRank="0.1359815479118598" support="1073" priorScore="8.925237832634173E-6" finalScore="0.8802830243139657" types=""/>
  </surfaceForm>
  <surfaceForm name="modified" offset="267">
    <resource label="Acoustic resonance" uri="Acoustic_resonance" contextualScore="0.9741306550760683" percentageOfSecondRank="0.03046458887381354" support="72" priorScore="5.98897599207512E-7" finalScore="0.9677576579748836" types=""/>
  </surfaceForm>
  <surfaceForm name="The" offset="233">
    <resource label="English articles" uri="English_articles" contextualScore="0.4591239938834855" percentageOfSecondRank="0.01116954603844357" support="5094" priorScore="4.237200514393148E-5" finalScore="0.9889149730161126" types=""/>
  </surfaceForm>
  <surfaceForm name="covalently" offset="323">
    <resource label="Covalent bond" uri="Covalent_bond" contextualScore="1.0" percentageOfSecondRank="0.0" support="1166" priorScore="9.698813898277209E-6" finalScore="1.0" types=""/>
  </surfaceForm>
  <surfaceForm name="fluorescent" offset="139">
    <resource label="Fluorescence" uri="Fluorescence" contextualScore="1.0" percentageOfSecondRank="3.5564689331920604E-19" support="2255" priorScore="1.875714008629083E-5" finalScore="1.0" types=""/>
  </surfaceForm>
  <surfaceForm name="magnetic" offset="297">
    <resource label="Magnetism" uri="Magnetism" contextualScore="0.030188548300905383" percentageOfSecondRank="0.07648616737190046" support="2480" priorScore="2.0628695083814304E-5" finalScore="0.21767509660385279" types=""/>
    <resource label="Magnetic field" uri="Magnetic_field" contextualScore="0.22863149107732095" percentageOfSecondRank="0.28429191170095375" support="5713" priorScore="4.752086089267384E-5" finalScore="0.7656746029159807" types=""/>
  </surfaceForm>
  <surfaceForm name="possessed" offset="285">
    <resource label="Demonic possession" uri="Demonic_possession" contextualScore="0.07427165152723507" percentageOfSecondRank="0.06407553587168822" support="470" priorScore="3.909470439271259E-6" finalScore="0.9038194930079043" types=""/>
  </surfaceForm>
  <surfaceForm name="concentration" offset="718">
    <resource label="Concentration" uri="Concentration" contextualScore="0.9999999999935199" percentageOfSecondRank="9.344623216026193E-14" support="1918" priorScore="1.5953966601111226E-5" finalScore="0.9999999999998863" types=""/>
  </surfaceForm>
  <surfaceForm name="coated" offset="251">
    <resource label="Thin film" uri="Thin_film" contextualScore="0.8995883461172918" percentageOfSecondRank="1.1748176238633717E-7" support="462" priorScore="3.842926261581536E-6" finalScore="0.22844067816313457" types=""/>
    <resource label="Coating" uri="Coating" contextualScore="0.10040942743480788" percentageOfSecondRank="0.2960766336134773" support="699" priorScore="5.814297525639596E-6" finalScore="0.771559293197584" types=""/>
  </surfaceForm>
  <surfaceForm name="imaging" offset="224">
    <resource label="Medical imaging" uri="Medical_imaging" contextualScore="0.9999999745945164" percentageOfSecondRank="5.509832538358845E-10" support="740" priorScore="6.155336436299429E-6" finalScore="0.9999999994489599" types=""/>
  </surfaceForm>
  <surfaceForm name="transmission electron microscopy" offset="847">
    <resource label="Transmission electron microscopy" uri="Transmission_electron_microscopy" contextualScore="1.0" percentageOfSecondRank="1.122374877521281E-21" support="296" priorScore="2.462134574519772E-6" finalScore="1.0" types=""/>
  </surfaceForm>
  <surfaceForm name="affinity" offset="500">
    <resource label="Dissociation constant" uri="Dissociation_constant" contextualScore="0.921486233435227" percentageOfSecondRank="0.0011474159680110328" support="777" priorScore="6.463103258114401E-6" finalScore="0.9985860215223985" types=""/>
  </surfaceForm>
  <surfaceForm name="nanoparticles" offset="648">
    <resource label="Nanoparticle" uri="Nanoparticle" contextualScore="1.0" percentageOfSecondRank="9.922473104375172E-17" support="1080" priorScore="8.983463988112681E-6" finalScore="1.0" types=""/>
  </surfaceForm>
  <surfaceForm name="high" offset="495">
    <resource label="Hypertension" uri="Hypertension" contextualScore="0.9999959996725216" percentageOfSecondRank="6.7187158159337115E-6" support="2395" priorScore="1.9921663195860992E-5" finalScore="0.9999908200175736" types="DBpedia:Disease"/>
  </surfaceForm>
  <surfaceForm name="cells" offset="21">
    <resource label="Cell (biology)" uri="Cell_(biology)" contextualScore="0.9999999986827106" percentageOfSecondRank="2.029064806317169E-13" support="14998" priorScore="1.2475369712380924E-4" finalScore="0.9999999999997726" types=""/>
  </surfaceForm>
  <surfaceForm name="cells" offset="972">
    <resource label="Cell (biology)" uri="Cell_(biology)" contextualScore="0.9999999986827106" percentageOfSecondRank="2.029064806317169E-13" support="14998" priorScore="1.2475369712380924E-4" finalScore="0.9999999999997726" types=""/>
  </surfaceForm>
  <surfaceForm name="core" offset="312">
    <resource label="Optical fiber" uri="Optical_fiber" contextualScore="0.9977357717595022" percentageOfSecondRank="0.001213953647787899" support="2078" priorScore="1.7284850154905695E-5" finalScore="0.9987874798910737" types=""/>
  </surfaceForm>
  <surfaceForm name="instruments" offset="880">
    <resource label="Measuring instrument" uri="Measuring_instrument" contextualScore="0.997678959364008" percentageOfSecondRank="5.552731127124702E-4" support="326" priorScore="2.7116752408562353E-6" finalScore="0.9989268722516331" types=""/>
  </surfaceForm>
  <surfaceForm name="detection" offset="57">
    <resource label="Spectroscopy" uri="Spectroscopy" contextualScore="0.9999999999821512" percentageOfSecondRank="1.4027115260442982E-11" support="1908" priorScore="1.587078637899907E-5" finalScore="0.9999999999860165" types=""/>
  </surfaceForm>
  <surfaceForm name="flow cytometry" offset="545">
    <resource label="Flow cytometry" uri="Flow_cytometry" contextualScore="1.0" percentageOfSecondRank="0.0" support="284" priorScore="2.3623183079851864E-6" finalScore="1.0" types=""/>
  </surfaceForm>
  <surfaceForm name="cells" offset="772">
    <resource label="Cell (biology)" uri="Cell_(biology)" contextualScore="0.9999999986827106" percentageOfSecondRank="2.029064806317169E-13" support="14998" priorScore="1.2475369712380924E-4" finalScore="0.9999999999997726" types=""/>
  </surfaceForm>
  <surfaceForm name="applications" offset="104">
    <resource label="Application software" uri="Application_software" contextualScore="0.1678927670346409" percentageOfSecondRank="0.0386975975639881" support="3689" priorScore="3.0685183937173776E-5" finalScore="0.9477387324357733" types=""/>
  </surfaceForm>
  <surfaceForm name="attached" offset="334">
    <resource label="Attachment theory" uri="Attachment_theory" contextualScore="0.999578018846949" percentageOfSecondRank="2.5981221564050023E-5" support="781" priorScore="6.496375346959263E-6" finalScore="0.9999597865054718" types=""/>
  </surfaceForm>
  <surfaceForm name="nanoparticles" offset="703">
    <resource label="Nanoparticle" uri="Nanoparticle" contextualScore="1.0" percentageOfSecondRank="9.922473104375172E-17" support="1080" priorScore="8.983463988112681E-6" finalScore="1.0" types=""/>
  </surfaceForm>
  <surfaceForm name="potential" offset="1042">
    <resource label="Electric field" uri="Electric_field" contextualScore="0.9389821080281223" percentageOfSecondRank="3.4914877997062186E-4" support="3043" priorScore="2.5311741588728602E-5" finalScore="0.9994541355528316" types=""/>
  </surfaceForm>
  <surfaceForm name="demonstrated" offset="1025">
    <resource label="Mathematical proof" uri="Mathematical_proof" contextualScore="0.9922009444118985" percentageOfSecondRank="6.929720681326119E-4" support="932" priorScore="7.752396700852795E-6" finalScore="0.9984484606436016" types=""/>
  </surfaceForm>
  <surfaceForm name="cancer cells" offset="416">
    <resource label="Cancer" uri="Cancer" contextualScore="0.9988601204987929" percentageOfSecondRank="2.1774808035609607E-4" support="18171" priorScore="1.5114678159999586E-4" finalScore="0.9997822993234928" types="DBpedia:Disease"/>
  </surfaceForm>
  <surfaceForm name="These" offset="979">
    <resource label="E. H. Carr" uri="E._H._Carr" contextualScore="0.9909827015386805" percentageOfSecondRank="3.2968659479048866E-4" support="92" priorScore="7.65258043431821E-7" finalScore="0.9993346600064559" types="DBpedia:Agent, Schema:Person, Http://xmlns.com/foaf/0.1/Person, DBpedia:Person"/>
  </surfaceForm>
  <surfaceForm name="magnetic nanoparticles" offset="151">
    <resource label="Magnetic nanoparticles" uri="Magnetic_nanoparticles" contextualScore="1.0" percentageOfSecondRank="0.0" support="33" priorScore="2.744947329701097E-7" finalScore="1.0" types=""/>
  </surfaceForm>
  <surfaceForm name="nanoparticles" offset="469">
    <resource label="Nanoparticle" uri="Nanoparticle" contextualScore="1.0" percentageOfSecondRank="9.922473104375172E-17" support="1080" priorScore="8.983463988112681E-6" finalScore="1.0" types=""/>
  </surfaceForm>
  <surfaceForm name="nanoparticles" offset="450">
    <resource label="Nanoparticle" uri="Nanoparticle" contextualScore="1.0" percentageOfSecondRank="9.922473104375172E-17" support="1080" priorScore="8.983463988112681E-6" finalScore="1.0" types=""/>
  </surfaceForm>
  <surfaceForm name="Fluorescence" offset="830">
    <resource label="Fluorescence" uri="Fluorescence" contextualScore="0.9621795076787273" percentageOfSecondRank="1.3345677768060725E-4" support="2255" priorScore="1.875714008629083E-5" finalScore="0.9998665610306036" types=""/>
  </surfaceForm>
  <surfaceForm name="cells" offset="512">
    <resource label="Cell (biology)" uri="Cell_(biology)" contextualScore="0.9999999986827106" percentageOfSecondRank="2.029064806317169E-13" support="14998" priorScore="1.2475369712380924E-4" finalScore="0.9999999999997726" types=""/>
  </surfaceForm>
  <surfaceForm name="dependent" offset="666">
    <resource label="Dependent and independent variables" uri="Dependent_and_independent_variables" contextualScore="0.1493336543036885" percentageOfSecondRank="0.002362632640769216" support="1142" priorScore="9.499181365208039E-6" finalScore="0.26894963863754373" types=""/>
    <resource label="Substance dependence" uri="Substance_dependence" contextualScore="0.8474598514992752" percentageOfSecondRank="0.36826347681374877" support="2459" priorScore="2.045401661737878E-5" finalScore="0.7303185234781412" types="DBpedia:Disease"/>
  </surfaceForm>
  <surfaceForm name="biomedical" offset="93">
    <resource label="Medical research" uri="Medical_research" contextualScore="0.6694146175745243" percentageOfSecondRank="0.004410027202492178" support="1041" priorScore="8.65906112187528E-6" finalScore="0.9955341266723032" types=""/>
  </surfaceForm>
  <surfaceForm name="detected" offset="745">
    <resource label="Medical diagnosis" uri="Medical_diagnosis" contextualScore="0.9999998241734301" percentageOfSecondRank="3.812489561303125E-8" support="959" priorScore="7.976983300555613E-6" finalScore="0.9999999618532919" types=""/>
  </surfaceForm>
  <surfaceForm name="cellular" offset="215">
    <resource label="Cell (biology)" uri="Cell_(biology)" contextualScore="0.9583561336046512" percentageOfSecondRank="8.852324198663053E-5" support="14998" priorScore="1.2475369712380924E-4" finalScore="0.9999114845937388" types=""/>
  </surfaceForm>
  <surfaceForm name="living" offset="50">
    <resource label="Life" uri="Life" contextualScore="0.995826327043536" percentageOfSecondRank="2.4813271375251323E-4" support="3497" priorScore="2.9088123672620413E-5" finalScore="0.9997212668509152" types=""/>
  </surfaceForm>
  <surfaceForm name="demonstrated" offset="529">
    <resource label="Mathematical proof" uri="Mathematical_proof" contextualScore="0.9922009444118985" percentageOfSecondRank="6.929720681326119E-4" support="932" priorScore="7.752396700852795E-6" finalScore="0.9984484606436016" types=""/>
  </surfaceForm>
  <surfaceForm name="number" offset="754">
    <resource label="Dimension (mathematics and physics)" uri="Dimension_(mathematics_and_physics)" contextualScore="0.9999885690828795" percentageOfSecondRank="7.762557920719013E-4" support="2117" priorScore="1.7609253021143097E-5" finalScore="0.9991760682153918" types=""/>
  </surfaceForm>
  <surfaceForm name="chitosan" offset="276">
    <resource label="Chitosan" uri="Chitosan" contextualScore="1.0" percentageOfSecondRank="0.0" support="91" priorScore="7.569400212206055E-7" finalScore="1.0" types="DBpedia:ChemicalSubstance, DBpedia:ChemicalCompound"/>
  </surfaceForm>
  <surfaceForm name="medical" offset="1063">
    <resource label="Medical research" uri="Medical_research" contextualScore="0.9999844162225707" percentageOfSecondRank="0.002432099786630041" support="1041" priorScore="8.65906112187528E-6" finalScore="0.9975738008914594" types=""/>
  </surfaceForm>
  <surfaceForm name="future" offset="1056">
    <resource label="Futures studies" uri="Futures_studies" contextualScore="0.7877290347068671" percentageOfSecondRank="0.1814936081801625" support="285" priorScore="2.370636330196402E-6" finalScore="0.10111335235215807" types=""/>
    <resource label="Wikipedia" uri="Wikipedia" contextualScore="0.08060641955793578" percentageOfSecondRank="0.26351032673824387" support="21139" priorScore="1.758346715228833E-4" finalScore="0.38371684936886097" types="Schema:CreativeWork, DBpedia:Work, Schema:WebPage, DBpedia:Website"/>
    <resource label="Future" uri="Future" contextualScore="0.009407872033939916" percentageOfSecondRank="0.7800485795932819" support="949" priorScore="7.893803078443457E-6" finalScore="0.4919140415189671" types=""/>
  </surfaceForm>
  <surfaceForm name="In" offset="118">
    <resource label="Indium" uri="Indium" contextualScore="0.9999956267007651" percentageOfSecondRank="6.265122880117945E-7" support="443" priorScore="3.6848838395684425E-6" finalScore="0.9999993704525131" types=""/>
  </surfaceForm>
  <surfaceForm name="The" offset="733">
    <resource label="English articles" uri="English_articles" contextualScore="0.4591239938834855" percentageOfSecondRank="0.01116954603844357" support="5094" priorScore="4.237200514393148E-5" finalScore="0.9889149730161126" types=""/>
  </surfaceForm>
  <surfaceForm name="nanoparticles" offset="32">
    <resource label="Nanoparticle" uri="Nanoparticle" contextualScore="1.0" percentageOfSecondRank="9.922473104375172E-17" support="1080" priorScore="8.983463988112681E-6" finalScore="1.0" types=""/>
  </surfaceForm>
  <surfaceForm name="SMMC" offset="430">
    <resource label="San Miguel Master Chorale" uri="San_Miguel_Master_Chorale" contextualScore="0.9999978906805118" percentageOfSecondRank="0.0" support="42" priorScore="3.493569328710487E-7" finalScore="0.9999999465233046" types=""/>
  </surfaceForm>
  <surfaceForm name="We" offset="360">
    <resource label="South Africa" uri="South_Africa" contextualScore="0.2361783944777671" percentageOfSecondRank="0.004082655812821162" support="56069" priorScore="4.6638318736063884E-4" finalScore="0.35443553937968547" types="Schema:Place, DBpedia:Place, DBpedia:PopulatedPlace, Schema:Country, DBpedia:Country"/>
    <resource label="Montana" uri="Montana" contextualScore="0.5542774425689718" percentageOfSecondRank="0.550358890069446" support="14470" priorScore="1.203617813962875E-4" finalScore="0.644008020539037" types="Schema:Place, DBpedia:Place, DBpedia:PopulatedPlace, DBpedia:Region, Schema:AdministrativeArea, DBpedia:AdministrativeRegion"/>
  </surfaceForm>
  <surfaceForm name="The" offset="465">
    <resource label="English articles" uri="English_articles" contextualScore="0.4591239938834855" percentageOfSecondRank="0.01116954603844357" support="5094" priorScore="4.237200514393148E-5" finalScore="0.9889149730161126" types=""/>
  </surfaceForm>
  <surfaceForm name="MRI" offset="818">
    <resource label="Magnetic resonance imaging" uri="Magnetic_resonance_imaging" contextualScore="1.0" percentageOfSecondRank="2.103924647599609E-25" support="2810" priorScore="2.33736424135154E-5" finalScore="1.0" types=""/>
  </surfaceForm>
  <surfaceForm name="Abstract" offset="0">
    <resource label="Abstract (summary)" uri="Abstract_(summary)" contextualScore="0.8354436681627718" percentageOfSecondRank="0.03887359310334144" support="222" priorScore="1.8466009308898289E-6" finalScore="0.36982420816748485" types=""/>
    <resource label="Abstraction" uri="Abstraction" contextualScore="0.1643221005885279" percentageOfSecondRank="0.6010056853586209" support="626" priorScore="5.207081904220869E-6" finalScore="0.6153422790781259" types=""/>
  </surfaceForm>
  <surfaceForm name="localization" offset="917">
    <resource label="Subcellular localization" uri="Subcellular_localization" contextualScore="0.997856417468314" percentageOfSecondRank="0.02226268026012153" support="60" priorScore="4.990813326729268E-7" finalScore="0.9755371386083143" types=""/>
  </surfaceForm>
  <surfaceForm name="magnetic resonance imaging" offset="564">
    <resource label="Magnetic resonance imaging" uri="Magnetic_resonance_imaging" contextualScore="0.9999999799578065" percentageOfSecondRank="1.1756689286678754E-11" support="2810" priorScore="2.33736424135154E-5" finalScore="0.9999999999882903" types=""/>
  </surfaceForm>
  <surfaceForm name="Labeling" offset="9">
    <resource label="Packaging and labeling" uri="Packaging_and_labeling" contextualScore="0.9934480566041731" percentageOfSecondRank="5.390394965009839E-4" support="1262" priorScore="1.0497344030553892E-5" finalScore="0.9993833487906558" types=""/>
  </surfaceForm>
  <surfaceForm name="fluorescent dye" offset="343">
    <resource label="Fluorophore" uri="Fluorophore" contextualScore="1.0" percentageOfSecondRank="6.573631813852974E-36" support="317" priorScore="2.6368130409552962E-6" finalScore="1.0" types=""/>
  </surfaceForm>
  <surfaceForm name="nanoparticles" offset="237">
    <resource label="Nanoparticle" uri="Nanoparticle" contextualScore="1.0" percentageOfSecondRank="9.922473104375172E-17" support="1080" priorScore="8.983463988112681E-6" finalScore="1.0" types=""/>
  </surfaceForm>
  <surfaceForm name="The" offset="592">
    <resource label="English articles" uri="English_articles" contextualScore="0.4591239938834855" percentageOfSecondRank="0.01116954603844357" support="5094" priorScore="4.237200514393148E-5" finalScore="0.9889149730161126" types=""/>
  </surfaceForm>
</annotation>