<annotation text="Abstract This article examines variation in family religious language policy in a Muslim community in West Africa. Taking an ethnographically grounded case study approach, I situate families’ choices with regards to their children’s religious (language) education within the larger linguistic, social, and cultural context, focusing on new influences on Islamic education and Arabic learning in the community and the wider region during a period of Islamic resurgence. I examine families’ religious education choices with particular attention to what they mean for children’s Arabic learning and what they say about families’ orientations toward Arabic. This article is based on a language socialization study of seven young Fulbe children into three languages (Fulfulde, Arabic, and French) at home, Qur’anic school, and public school in northern Cameroon. Changes in the religious, linguistic, and educational landscape of the region are reflected in the variation within and among four focal families with respect to how they organized and envisioned their children’s religious study and Arabic language learning. In presenting ethnographic research conducted at the intersection of religious language policy, language education policy, and family language policy, my goal is to further our understanding of how private choices are connected to forces in the public sphere, giving rise to changes in the ways faith, language, and learning are practiced and conceptualized.">
  <surfaceForm name="forces" offset="1348">
    <resource label="Force" uri="Force" contextualScore="0.8564191237320997" percentageOfSecondRank="0.0018278318992102844" support="4917" priorScore="4.089971521254635E-5" finalScore="0.9981507514379873" types=""/>
  </surfaceForm>
  <surfaceForm name="conceptualized" offset="1460">
    <resource label="Concept" uri="Concept" contextualScore="0.9999283320701956" percentageOfSecondRank="1.080715718124694E-6" support="1658" priorScore="1.3791280826195208E-5" finalScore="0.9999989192854328" types=""/>
  </surfaceForm>
  <surfaceForm name="study" offset="704">
    <resource label="Research" uri="Research" contextualScore="0.9334599389531902" percentageOfSecondRank="0.00233667091965937" support="9112" priorScore="7.579381838859514E-5" finalScore="0.9976649936907105" types=""/>
  </surfaceForm>
  <surfaceForm name="Arabic" offset="646">
    <resource label="Arabic language" uri="Arabic_language" contextualScore="0.005526890548186737" percentageOfSecondRank="0.009763359835142826" support="24179" priorScore="2.0112145904497826E-4" finalScore="0.9900439093671864" types="Schema:Language, DBpedia:Language"/>
  </surfaceForm>
  <surfaceForm name="language education" offset="1213">
    <resource label="Language education" uri="Language_education" contextualScore="1.0" percentageOfSecondRank="0.0" support="266" priorScore="2.2125939081833087E-6" finalScore="1.0" types=""/>
  </surfaceForm>
  <surfaceForm name="organized" offset="1029">
    <resource label="Organization" uri="Organization" contextualScore="0.9834915504314844" percentageOfSecondRank="0.001290881051641136" support="3730" priorScore="3.1026222847833615E-5" finalScore="0.9987074601510457" types=""/>
  </surfaceForm>
  <surfaceForm name="Arabic" offset="772">
    <resource label="Arabic language" uri="Arabic_language" contextualScore="0.005526890548186737" percentageOfSecondRank="0.009763359835142826" support="24179" priorScore="2.0112145904497826E-4" finalScore="0.9900439093671864" types="Schema:Language, DBpedia:Language"/>
  </surfaceForm>
  <surfaceForm name="This" offset="9">
    <resource label="Breast" uri="Breast" contextualScore="0.9802999879545602" percentageOfSecondRank="0.017721644072189024" support="3027" priorScore="2.5178653233349152E-5" finalScore="0.9825864224623069" types="DBpedia:AnatomicalStructure"/>
  </surfaceForm>
  <surfaceForm name="education" offset="254">
    <resource label="Education" uri="Education" contextualScore="0.7220223321886319" percentageOfSecondRank="6.813120242926324E-5" support="18006" priorScore="1.4977430793514533E-4" finalScore="0.9999318617021004" types=""/>
  </surfaceForm>
  <surfaceForm name="presenting" offset="1120">
    <resource label="Presentation" uri="Presentation" contextualScore="0.9999483179413735" percentageOfSecondRank="0.0016506566644073936" support="254" priorScore="2.112777641648723E-6" finalScore="0.998351030824555" types=""/>
  </surfaceForm>
  <surfaceForm name="French" offset="784">
    <resource label="French language" uri="French_language" contextualScore="0.9852585488204056" percentageOfSecondRank="1.9621825991399892E-5" support="46464" priorScore="3.864885840219145E-4" finalScore="0.9999671728048211" types="Schema:Language, DBpedia:Language"/>
  </surfaceForm>
  <surfaceForm name="region" offset="929">
    <resource label="Region" uri="Region" contextualScore="0.8688865105289901" percentageOfSecondRank="0.0060740254878801315" support="2776" priorScore="2.3090829658334076E-5" finalScore="0.9926531221728655" types=""/>
  </surfaceForm>
  <surfaceForm name="public school" offset="822">
    <resource label="State school" uri="State_school" contextualScore="0.07341337731639733" percentageOfSecondRank="0.004622841974838782" support="11603" priorScore="9.651401171673281E-5" finalScore="0.9907219670565485" types=""/>
  </surfaceForm>
  <surfaceForm name="grounded" offset="142">
    <resource label="Grounded theory" uri="Grounded_theory" contextualScore="0.9999999998663043" percentageOfSecondRank="9.083990392683182E-8" support="48" priorScore="3.992650661383414E-7" finalScore="0.9999999091395507" types=""/>
  </surfaceForm>
  <surfaceForm name="West Africa" offset="102">
    <resource label="West Africa" uri="West_Africa" contextualScore="0.9999982231937434" percentageOfSecondRank="3.1304597509953294E-9" support="4474" priorScore="3.72148313729779E-5" finalScore="0.9999999966963742" types=""/>
  </surfaceForm>
  <surfaceForm name="region" offset="423">
    <resource label="Region" uri="Region" contextualScore="0.8688865105289901" percentageOfSecondRank="0.0060740254878801315" support="2776" priorScore="2.3090829658334076E-5" finalScore="0.9926531221728655" types=""/>
  </surfaceForm>
  <surfaceForm name="focusing" offset="324">
    <resource label="Attention" uri="Attention" contextualScore="0.9994092002429166" percentageOfSecondRank="0.04263492703038049" support="1766" priorScore="1.4689627225006477E-5" finalScore="0.9591084118919011" types=""/>
  </surfaceForm>
  <surfaceForm name="northern" offset="839">
    <resource label="Northern Europe" uri="Northern_Europe" contextualScore="0.9925383601013796" percentageOfSecondRank="0.017923156837593088" support="1114" priorScore="9.266276743294006E-6" finalScore="0.9820760122457987" types=""/>
  </surfaceForm>
  <surfaceForm name="Arabic" offset="376">
    <resource label="Arabic language" uri="Arabic_language" contextualScore="0.005526890548186737" percentageOfSecondRank="0.009763359835142826" support="24179" priorScore="2.0112145904497826E-4" finalScore="0.9900439093671864" types="Schema:Language, DBpedia:Language"/>
  </surfaceForm>
  <surfaceForm name="family" offset="44">
    <resource label="Family" uri="Family" contextualScore="0.9948274517240261" percentageOfSecondRank="2.582009273206233E-5" support="4491" priorScore="3.735623775056857E-5" finalScore="0.9999646765744237" types=""/>
  </surfaceForm>
  <surfaceForm name="In" offset="1117">
    <resource label="Indium" uri="Indium" contextualScore="0.7022158699846832" percentageOfSecondRank="0.015157633969864418" support="443" priorScore="3.6848838395684425E-6" finalScore="0.9832569872438007" types=""/>
  </surfaceForm>
  <surfaceForm name="languages" offset="751">
    <resource label="Language" uri="Language" contextualScore="0.9998858132079065" percentageOfSecondRank="1.9354830407533437E-8" support="15854" priorScore="1.3187392413660967E-4" finalScore="0.999999979193831" types=""/>
  </surfaceForm>
  <surfaceForm name="choices" offset="509">
    <resource label="Decision making" uri="Decision_making" contextualScore="0.9883830355515756" percentageOfSecondRank="0.0686351283238833" support="1151" priorScore="9.574043565108977E-6" finalScore="0.9357480562633914" types=""/>
  </surfaceForm>
  <surfaceForm name="Changes" offset="858">
    <resource label="Changes (novel)" uri="Changes_(novel)" contextualScore="0.5827688505011911" percentageOfSecondRank="0.016285907618112383" support="88" priorScore="7.319859545869592E-7" finalScore="0.9836599148249461" types="Schema:CreativeWork, DBpedia:Work, DBpedia:WrittenWork, Http://purl.org/ontology/bibo/Book, Schema:Book, DBpedia:Book"/>
  </surfaceForm>
  <surfaceForm name="families" offset="616">
    <resource label="Family" uri="Family" contextualScore="0.9987371427317414" percentageOfSecondRank="2.554949789297643E-5" support="4491" priorScore="3.735623775056857E-5" finalScore="0.9999744390173161" types=""/>
  </surfaceForm>
  <surfaceForm name="Arabic" offset="1091">
    <resource label="Arabic language" uri="Arabic_language" contextualScore="0.005526890548186737" percentageOfSecondRank="0.009763359835142826" support="24179" priorScore="2.0112145904497826E-4" finalScore="0.9900439093671864" types="Schema:Language, DBpedia:Language"/>
  </surfaceForm>
  <surfaceForm name="language" offset="1419">
    <resource label="Language" uri="Language" contextualScore="0.9826153312777557" percentageOfSecondRank="1.3072740502361494E-5" support="15854" priorScore="1.3187392413660967E-4" finalScore="0.9999869045584808" types=""/>
  </surfaceForm>
  <surfaceForm name="ethnographically" offset="125">
    <resource label="Ethnography" uri="Ethnography" contextualScore="1.0" percentageOfSecondRank="2.471315948692162E-19" support="1592" priorScore="1.3242291360254989E-5" finalScore="1.0" types=""/>
  </surfaceForm>
  <surfaceForm name="rise" offset="1384">
    <resource label="Current sea level rise" uri="Current_sea_level_rise" contextualScore="0.5132746729271367" percentageOfSecondRank="0.07287974713645393" support="538" priorScore="4.4750959496339095E-6" finalScore="0.8953406755064799" types=""/>
  </surfaceForm>
  <surfaceForm name="Abstract" offset="0">
    <resource label="Abstraction" uri="Abstraction" contextualScore="0.998852057789092" percentageOfSecondRank="0.005563133665720846" support="626" priorScore="5.207081904220869E-6" finalScore="0.9942895027252902" types=""/>
  </surfaceForm>
  <surfaceForm name="context" offset="315">
    <resource label="Context (language use)" uri="Context_(language_use)" contextualScore="0.5167244255580142" percentageOfSecondRank="0.010868550777992895" support="218" priorScore="1.8133288420449672E-6" finalScore="0.9892482804080418" types=""/>
  </surfaceForm>
  <surfaceForm name="reflected" offset="940">
    <resource label="Reflection (physics)" uri="Reflection_(physics)" contextualScore="0.4036198908647044" percentageOfSecondRank="0.0031759847836958224" support="932" priorScore="7.752396700852795E-6" finalScore="0.9955622380278211" types=""/>
  </surfaceForm>
  <surfaceForm name="ways" offset="1407">
    <resource label="Culture" uri="Culture" contextualScore="0.9999999996604174" percentageOfSecondRank="1.2376229252330095E-11" support="9267" priorScore="7.708311183133353E-5" finalScore="0.9999999999810143" types=""/>
  </surfaceForm>
  <surfaceForm name="language learning" offset="1098">
    <resource label="Language acquisition" uri="Language_acquisition" contextualScore="0.9720906156092306" percentageOfSecondRank="1.1554545026565665E-4" support="692" priorScore="5.756071370161089E-6" finalScore="0.9998295677802612" types=""/>
  </surfaceForm>
  <surfaceForm name="variation" offset="957">
    <resource label="Sociolinguistics" uri="Sociolinguistics" contextualScore="0.9999999835604286" percentageOfSecondRank="3.5959790258053814E-9" support="354" priorScore="2.9445798627702678E-6" finalScore="0.9999999963981736" types=""/>
  </surfaceForm>
  <surfaceForm name="Arabic" offset="576">
    <resource label="Arabic language" uri="Arabic_language" contextualScore="0.005526890548186737" percentageOfSecondRank="0.009763359835142826" support="24179" priorScore="2.0112145904497826E-4" finalScore="0.9900439093671864" types="Schema:Language, DBpedia:Language"/>
  </surfaceForm>
  <surfaceForm name="private" offset="1315">
    <resource label="Private property" uri="Private_property" contextualScore="0.6245084345942236" percentageOfSecondRank="0.423017283622362" support="816" priorScore="6.787506124351804E-6" finalScore="0.1935403060419021" types=""/>
    <resource label="Private sector" uri="Private_sector" contextualScore="0.25602377017887135" percentageOfSecondRank="0.2917639072742538" support="1354" priorScore="1.1262602073985714E-5" finalScore="0.6633456065557042" types=""/>
  </surfaceForm>
  <surfaceForm name="linguistic" offset="282">
    <resource label="Linguistics" uri="Linguistics" contextualScore="3.877000267525278E-4" percentageOfSecondRank="0.3826288429398822" support="6562" priorScore="5.458286174999575E-5" finalScore="0.11273159675593428" types=""/>
    <resource label="Language" uri="Language" contextualScore="0.006830126460747591" percentageOfSecondRank="0.1337637679958967" support="15854" priorScore="1.3187392413660967E-4" finalScore="0.8427663069374092" types=""/>
  </surfaceForm>
  <surfaceForm name="families" offset="182">
    <resource label="Family" uri="Family" contextualScore="0.9987371427317414" percentageOfSecondRank="2.554949789297643E-5" support="4491" priorScore="3.735623775056857E-5" finalScore="0.9999744390173161" types=""/>
  </surfaceForm>
  <surfaceForm name="Islamic education" offset="354">
    <resource label="Islamic studies" uri="Islamic_studies" contextualScore="0.9917761521080081" percentageOfSecondRank="0.008544522369195744" support="520" priorScore="4.325371549832031E-6" finalScore="0.9915278679525513" types=""/>
  </surfaceForm>
  <surfaceForm name="language policy" offset="1196">
    <resource label="Language policy" uri="Language_policy" contextualScore="0.9999999496837985" percentageOfSecondRank="9.418102747857926E-8" support="114" priorScore="9.482545320785608E-7" finalScore="0.9999999056768774" types=""/>
  </surfaceForm>
  <surfaceForm name="public sphere" offset="1362">
    <resource label="Public sphere" uri="Public_sphere" contextualScore="1.0" percentageOfSecondRank="0.0" support="393" priorScore="3.26898272900767E-6" finalScore="1.0" types=""/>
  </surfaceForm>
  <surfaceForm name="language policy" offset="1251">
    <resource label="Language policy" uri="Language_policy" contextualScore="0.9999999496837985" percentageOfSecondRank="9.418102747857926E-8" support="114" priorScore="9.482545320785608E-7" finalScore="0.9999999056768774" types=""/>
  </surfaceForm>
  <surfaceForm name="Cameroon" offset="848">
    <resource label="Cameroon" uri="Cameroon" contextualScore="0.9998516894568267" percentageOfSecondRank="1.7834824711029324E-8" support="10591" priorScore="8.809617323898279E-5" finalScore="0.9999999820331597" types="Schema:Place, DBpedia:Place, DBpedia:PopulatedPlace, Schema:Country, DBpedia:Country"/>
  </surfaceForm>
  <surfaceForm name="ethnographic" offset="1131">
    <resource label="Ethnography" uri="Ethnography" contextualScore="0.9888066127623443" percentageOfSecondRank="6.364514749805032E-5" support="1592" priorScore="1.3242291360254989E-5" finalScore="0.9999363589028777" types=""/>
  </surfaceForm>
  <surfaceForm name="social" offset="294">
    <resource label="Social" uri="Social" contextualScore="0.5097821750748764" percentageOfSecondRank="0.028337211070714713" support="2304" priorScore="1.9164723174640385E-5" finalScore="0.9610016067804532" types=""/>
  </surfaceForm>
  <surfaceForm name="connected" offset="1335">
    <resource label="Connected space" uri="Connected_space" contextualScore="0.16840412994694914" percentageOfSecondRank="0.04211534173556652" support="971" priorScore="8.076799567090197E-6" finalScore="0.9512741539062504" types=""/>
  </surfaceForm>
  <surfaceForm name="Qur&apos;anic school" offset="801">
    <resource label="Madrasa" uri="Madrasa" contextualScore="1.0" percentageOfSecondRank="3.916961745926774E-20" support="1929" priorScore="1.6045464845434595E-5" finalScore="1.0" types=""/>
  </surfaceForm>
  <surfaceForm name="variation" offset="31">
    <resource label="Sociolinguistics" uri="Sociolinguistics" contextualScore="0.9999999835604286" percentageOfSecondRank="3.5959790258053814E-9" support="354" priorScore="2.9445798627702678E-6" finalScore="0.9999999963981736" types=""/>
  </surfaceForm>
  <surfaceForm name="language" offset="244">
    <resource label="Language" uri="Language" contextualScore="0.9826153312777557" percentageOfSecondRank="1.3072740502361494E-5" support="15854" priorScore="1.3187392413660967E-4" finalScore="0.9999869045584808" types=""/>
  </surfaceForm>
  <surfaceForm name="linguistic" offset="884">
    <resource label="Linguistics" uri="Linguistics" contextualScore="3.877000267525278E-4" percentageOfSecondRank="0.3826288429398822" support="6562" priorScore="5.458286174999575E-5" finalScore="0.11273159675593428" types=""/>
    <resource label="Language" uri="Language" contextualScore="0.006830126460747591" percentageOfSecondRank="0.1337637679958967" support="15854" priorScore="1.3187392413660967E-4" finalScore="0.8427663069374092" types=""/>
  </surfaceForm>
  <surfaceForm name="article" offset="14">
    <resource label="Article (grammar)" uri="Article_(grammar)" contextualScore="0.9998782958836814" percentageOfSecondRank="9.545619968876656E-6" support="1188" priorScore="9.881810386923949E-6" finalScore="0.9999803219085455" types=""/>
  </surfaceForm>
  <surfaceForm name="intersection" offset="1170">
    <resource label="Intersectionality" uri="Intersectionality" contextualScore="0.9994131778413633" percentageOfSecondRank="0.026912162880213992" support="80" priorScore="6.654417768972357E-7" finalScore="0.9658985518358227" types=""/>
  </surfaceForm>
  <surfaceForm name="This" offset="654">
    <resource label="Breast" uri="Breast" contextualScore="0.9802999879545602" percentageOfSecondRank="0.017721644072189024" support="3027" priorScore="2.5178653233349152E-5" finalScore="0.9825864224623069" types="DBpedia:AnatomicalStructure"/>
  </surfaceForm>
  <surfaceForm name="educational" offset="900">
    <resource label="Education" uri="Education" contextualScore="0.9916843847853574" percentageOfSecondRank="3.251737114787689E-6" support="18006" priorScore="1.4977430793514533E-4" finalScore="0.9999967447261731" types=""/>
  </surfaceForm>
  <surfaceForm name="religious education" offset="489">
    <resource label="Islamic studies" uri="Islamic_studies" contextualScore="0.9991961580877373" percentageOfSecondRank="0.05241980283149293" support="520" priorScore="4.325371549832031E-6" finalScore="0.9435861220824228" types=""/>
  </surfaceForm>
  <surfaceForm name="focal" offset="989">
    <resource label="Focus (optics)" uri="Focus_(optics)" contextualScore="0.04242544982125449" percentageOfSecondRank="2.86569292462514E-5" support="1003" priorScore="8.342976277849091E-6" finalScore="0.40606360988704265" types=""/>
    <resource label="Focus (linguistics)" uri="Focus_(linguistics)" contextualScore="0.957527484667364" percentageOfSecondRank="0.683695597448899" support="130" priorScore="1.0813428874580078E-6" finalScore="0.5939245643853848" types=""/>
  </surfaceForm>
  <surfaceForm name="Muslim community" offset="82">
    <resource label="Ummah" uri="Ummah" contextualScore="0.9997515942380083" percentageOfSecondRank="3.3503486976108665E-6" support="403" priorScore="3.3521629511198245E-6" finalScore="0.9999966473385979" types=""/>
  </surfaceForm>
  <surfaceForm name="Fulbe" offset="725">
    <resource label="Fula people" uri="Fula_people" contextualScore="1.0" percentageOfSecondRank="0.0" support="1289" priorScore="1.072193063025671E-5" finalScore="1.0" types="DBpedia:EthnicGroup"/>
  </surfaceForm>
  <surfaceForm name="language" offset="681">
    <resource label="Language" uri="Language" contextualScore="0.9826153312777557" percentageOfSecondRank="1.3072740502361494E-5" support="15854" priorScore="1.3187392413660967E-4" finalScore="0.9999869045584808" types=""/>
  </surfaceForm>
  <surfaceForm name="wider" offset="417">
    <resource label="Misnagdim" uri="Misnagdim" contextualScore="0.9999998259796863" percentageOfSecondRank="0.0" support="119" priorScore="9.89844643134638E-7" finalScore="0.9999999984428314" types=""/>
  </surfaceForm>
  <surfaceForm name="based" offset="670">
    <resource label="English-based creole languages" uri="English-based_creole_languages" contextualScore="0.983178673469736" percentageOfSecondRank="0.06657349528164075" support="117" priorScore="9.732085987122072E-7" finalScore="0.2475317690178211" types=""/>
    <resource label="Sampling (music)" uri="Sampling_(music)" contextualScore="0.013650175715804664" percentageOfSecondRank="0.33722037977022296" support="3570" priorScore="2.969533929403914E-5" finalScore="0.7340356154823313" types=""/>
  </surfaceForm>
  <surfaceForm name="respect" offset="1009">
    <resource label="Respect" uri="Respect" contextualScore="1.0" percentageOfSecondRank="0.0" support="375" priorScore="3.119258329205792E-6" finalScore="1.0" types=""/>
  </surfaceForm>
  <surfaceForm name="attention" offset="533">
    <resource label="Attention" uri="Attention" contextualScore="0.9999968957667285" percentageOfSecondRank="3.3712019401622677E-9" support="1766" priorScore="1.4689627225006477E-5" finalScore="0.9999999966153155" types=""/>
  </surfaceForm>
  <surfaceForm name="choices" offset="1323">
    <resource label="Decision making" uri="Decision_making" contextualScore="0.9883830355515756" percentageOfSecondRank="0.0686351283238833" support="1151" priorScore="9.574043565108977E-6" finalScore="0.9357480562633914" types=""/>
  </surfaceForm>
  <surfaceForm name="Fulfulde" offset="762">
    <resource label="Fula language" uri="Fula_language" contextualScore="1.0" percentageOfSecondRank="0.0" support="332" priorScore="2.761583374123528E-6" finalScore="1.0" types="Schema:Language, DBpedia:Language"/>
  </surfaceForm>
  <surfaceForm name="young" offset="719">
    <resource label="Youth" uri="Youth" contextualScore="0.96462952222555" percentageOfSecondRank="0.0021114751609920875" support="1573" priorScore="1.3084248938241896E-5" finalScore="0.9975229446748051" types=""/>
  </surfaceForm>
  <surfaceForm name="families" offset="479">
    <resource label="Family" uri="Family" contextualScore="0.9987371427317414" percentageOfSecondRank="2.554949789297643E-5" support="4491" priorScore="3.735623775056857E-5" finalScore="0.9999744390173161" types=""/>
  </surfaceForm>
  <surfaceForm name="cultural" offset="306">
    <resource label="Culture" uri="Culture" contextualScore="0.49649030380110654" percentageOfSecondRank="0.002285676254978963" support="9267" priorScore="7.708311183133353E-5" finalScore="0.9971758483689089" types=""/>
  </surfaceForm>
  <surfaceForm name="article" offset="659">
    <resource label="Article (grammar)" uri="Article_(grammar)" contextualScore="0.9998782958836814" percentageOfSecondRank="9.545619968876656E-6" support="1188" priorScore="9.881810386923949E-6" finalScore="0.9999803219085455" types=""/>
  </surfaceForm>
  <surfaceForm name="period" offset="439">
    <resource label="Periodization" uri="Periodization" contextualScore="0.9986779727748316" percentageOfSecondRank="0.06253445049487506" support="260" priorScore="2.1626857749160156E-6" finalScore="0.940372792749975" types=""/>
  </surfaceForm>
  <surfaceForm name="conducted" offset="1153">
    <resource label="Conducting" uri="Conducting" contextualScore="8.835525915383039E-4" percentageOfSecondRank="0.001146932113206575" support="8875" priorScore="7.382244712453707E-5" finalScore="0.43833733082776705" types=""/>
    <resource label="Electrical resistivity and conductivity" uri="Electrical_resistivity_and_conductivity" contextualScore="0.9958822688590813" percentageOfSecondRank="0.781425980513352" support="1451" priorScore="1.2069450228473612E-5" finalScore="0.5609454276652084" types=""/>
  </surfaceForm>
  <surfaceForm name="case study" offset="151">
    <resource label="Case study" uri="Case_study" contextualScore="0.9999724095454213" percentageOfSecondRank="2.304742120020046E-8" support="333" priorScore="2.7699013963347435E-6" finalScore="0.9999999769498802" types=""/>
  </surfaceForm>
  <surfaceForm name="landscape" offset="912">
    <resource label="Landscape" uri="Landscape" contextualScore="0.8864913110778315" percentageOfSecondRank="0.002790788466749074" support="1957" priorScore="1.6278369467348628E-5" finalScore="0.9964239012688398" types=""/>
  </surfaceForm>
  <surfaceForm name="Islamic resurgence" offset="449">
    <resource label="Islamic revival" uri="Islamic_revival" contextualScore="0.9999999999968168" percentageOfSecondRank="0.0" support="60" priorScore="4.990813326729268E-7" finalScore="1.0" types=""/>
  </surfaceForm>
  <surfaceForm name="goal" offset="1271">
    <resource label="Goal" uri="Goal" contextualScore="0.9999999999990905" percentageOfSecondRank="1.029733315125529E-13" support="954" priorScore="7.935393189499535E-6" finalScore="0.9999999999997726" types=""/>
  </surfaceForm>
  <surfaceForm name="family" offset="1244">
    <resource label="Family" uri="Family" contextualScore="0.9948274517240261" percentageOfSecondRank="2.582009273206233E-5" support="4491" priorScore="3.735623775056857E-5" finalScore="0.9999646765744237" types=""/>
  </surfaceForm>
  <surfaceForm name="study" offset="1081">
    <resource label="Research" uri="Research" contextualScore="0.9334599389531902" percentageOfSecondRank="0.00233667091965937" support="9112" priorScore="7.579381838859514E-5" finalScore="0.9976649936907105" types=""/>
  </surfaceForm>
  <surfaceForm name="orientations" offset="626">
    <resource label="Sexual orientation" uri="Sexual_orientation" contextualScore="0.9896717670056739" percentageOfSecondRank="0.0010206866024248216" support="3146" priorScore="2.6168497876483792E-5" finalScore="0.998979495775429" types=""/>
  </surfaceForm>
  <surfaceForm name="language policy" offset="61">
    <resource label="Language policy" uri="Language_policy" contextualScore="0.9999999496837985" percentageOfSecondRank="9.418102747857926E-8" support="114" priorScore="9.482545320785608E-7" finalScore="0.9999999056768774" types=""/>
  </surfaceForm>
  <surfaceForm name="choices" offset="192">
    <resource label="Decision making" uri="Decision_making" contextualScore="0.9883830355515756" percentageOfSecondRank="0.0686351283238833" support="1151" priorScore="9.574043565108977E-6" finalScore="0.9357480562633914" types=""/>
  </surfaceForm>
  <surfaceForm name="families" offset="995">
    <resource label="Family" uri="Family" contextualScore="0.9987371427317414" percentageOfSecondRank="2.554949789297643E-5" support="4491" priorScore="3.735623775056857E-5" finalScore="0.9999744390173161" types=""/>
  </surfaceForm>
  <surfaceForm name="socialization" offset="690">
    <resource label="Socialization" uri="Socialization" contextualScore="0.9999999551700977" percentageOfSecondRank="5.635254249032221E-9" support="381" priorScore="3.1691664624730846E-6" finalScore="0.9999999943647708" types=""/>
  </surfaceForm>
  <surfaceForm name="faith" offset="1412">
    <resource label="Faith" uri="Faith" contextualScore="0.0245412272365248" percentageOfSecondRank="0.010521635028961474" support="2238" priorScore="1.8615733708700167E-5" finalScore="0.22769566813622344" types=""/>
    <resource label="Religion" uri="Religion" contextualScore="0.9707883867013573" percentageOfSecondRank="0.29574421161612846" support="12849" priorScore="1.0687826739190726E-4" finalScore="0.7699074375520458" types=""/>
  </surfaceForm>
</annotation>